dods/analyze/__init__.py
dods/analyze/core/__init__.py
dods/analyze/core/base.py
dods/analyze/core/feature_stats.py
dods/analyze/core/logging_setup.py
dods/analyze/core/analyzer/__init__.py
dods/analyze/core/analyzer/info_utils.py
dods/analyze/core/analyzer/main.py
dods/analyze/core/analyzer/relations_engine.py
dods/analyze/core/analyzer/stats_compute.py
dods/analyze/core/analyzer/summary.py
dods/analyze/core/analyzer/threshold_engine.py
dods/analyze/core/analyzer/deep_analysis/__init__.py
dods/analyze/core/analyzer/deep_analysis/categoricals.py
dods/analyze/core/analyzer/deep_analysis/distributions.py
dods/analyze/core/analyzer/deep_analysis/missing.py
dods/analyze/core/analyzer/deep_analysis/outliers.py
dods/analyze/core/analyzer/deep_analysis/relations.py
dods/analyze/core/analyzer/plot_config/__init__.py
dods/analyze/core/analyzer/plot_config/correlation.py
dods/analyze/core/analyzer/plot_config/distribution.py
dods/analyze/core/analyzer/plot_config/flags.py
dods/analyze/core/analyzer/plot_config/missing.py
dods/analyze/core/analyzer/plot_config/outliers.py
dods/analyze/core/analyzer/relations/__init__.py
dods/analyze/core/analyzer/relations/classifier.py
dods/analyze/core/analyzer/relations/config.py
dods/analyze/core/analyzer/relations/correlation.py
dods/analyze/core/analyzer/relations/distribution.py
dods/analyze/core/analyzer/relations/engine.py
dods/analyze/core/analyzer/relations/grouping.py
dods/analyze/core/analyzer/relations/mutual_info_calculator.py
dods/analyze/core/analyzer/summaries/__init__.py
dods/analyze/core/analyzer/summaries/analysis_options.py
dods/analyze/core/analyzer/summaries/cast_suggestions.py
dods/analyze/core/analyzer/summaries/correlation_alerts.py
dods/analyze/core/analyzer/summaries/dataset_summary.py
dods/analyze/core/analyzer/summaries/missing_summary.py
dods/analyze/core/analyzer/summaries/table_categorical.py
dods/analyze/core/analyzer/summaries/table_numeric.py
dods/analyze/core/analyzer/utils/__init__.py
dods_analyze-0.1.0.dist-info/licenses/LICENSE
dods_analyze-0.1.0.dist-info/licenses/NOTICE
dods_analyze-0.1.0.dist-info/METADATA
dods_analyze-0.1.0.dist-info/WHEEL
dods_analyze-0.1.0.dist-info/top_level.txt
dods_analyze-0.1.0.dist-info/RECORD
